owasp_dependency_track_client-4.13.7.dist-info/licenses/LICENSE
owasp_dt/__init__.py
owasp_dt/client.py
owasp_dt/errors.py
owasp_dt/types.py
owasp_dt/api/__init__.py
owasp_dt/api/acl/__init__.py
owasp_dt/api/acl/delete_mapping.py
owasp_dt/api/acl/retrieve_projects.py
owasp_dt/api/analysis/__init__.py
owasp_dt/api/analysis/retrieve_analysis.py
owasp_dt/api/analysis/update_analysis.py
owasp_dt/api/badge/__init__.py
owasp_dt/api/badge/get_project_policy_violations_badge.py
owasp_dt/api/badge/get_project_policy_violations_badge_1.py
owasp_dt/api/badge/get_project_vulnerabilities_badge.py
owasp_dt/api/badge/get_project_vulnerabilities_badge_1.py
owasp_dt/api/bom/__init__.py
owasp_dt/api/bom/export_component_as_cyclone_dx.py
owasp_dt/api/bom/export_project_as_cyclone_dx.py
owasp_dt/api/bom/is_token_being_processed.py
owasp_dt/api/bom/upload_bom.py
owasp_dt/api/bom/upload_bom_base_64_encoded.py
owasp_dt/api/calculator/__init__.py
owasp_dt/api/calculator/get_cvss_scores.py
owasp_dt/api/calculator/get_owasp_rr_scores.py
owasp_dt/api/component/__init__.py
owasp_dt/api/component/create_component.py
owasp_dt/api/component/delete_component.py
owasp_dt/api/component/get_all_components.py
owasp_dt/api/component/get_component_by_hash.py
owasp_dt/api/component/get_component_by_identity.py
owasp_dt/api/component/get_component_by_uuid.py
owasp_dt/api/component/get_dependency_graph_for_component.py
owasp_dt/api/component/identify_internal_components.py
owasp_dt/api/component/update_component.py
owasp_dt/api/component_property/__init__.py
owasp_dt/api/component_property/create_property.py
owasp_dt/api/component_property/delete_property.py
owasp_dt/api/component_property/get_properties.py
owasp_dt/api/config_property/__init__.py
owasp_dt/api/config_property/get_config_properties.py
owasp_dt/api/config_property/get_public_config_property.py
owasp_dt/api/config_property/update_config_property.py
owasp_dt/api/config_property/update_config_property_1.py
owasp_dt/api/cwe/__init__.py
owasp_dt/api/cwe/get_cwe.py
owasp_dt/api/cwe/get_cwes.py
owasp_dependency_track_client-4.13.7.dist-info/METADATA
owasp_dependency_track_client-4.13.7.dist-info/WHEEL
owasp_dependency_track_client-4.13.7.dist-info/top_level.txt
owasp_dependency_track_client-4.13.7.dist-info/RECORD
