Metadata-Version: 2.4
Name: owasp-dependency-track-client
Version: 4.13.7
Summary: Inofficial OWASP Dependency Track API Python client
License-File: LICENSE
Requires-Dist: attrs>=22.1.0
Requires-Dist: httpx>=0.23.0
Requires-Dist: python-dateutil>=2.8.2
Provides-Extra: build
Requires-Dist: build; extra == "build"
Requires-Dist: twine; extra == "build"
Provides-Extra: test
Requires-Dist: pytest>=7; extra == "test"
Requires-Dist: pytest-depends; extra == "test"
Requires-Dist: pytest-cov; extra == "test"
Requires-Dist: dotenv==0.9.9; extra == "test"
Requires-Dist: openapi-python-client; extra == "test"
Requires-Dist: tinystream==0.1.18; extra == "test"
Requires-Dist: is_empty==1.0.1; extra == "test"
Dynamic: license-file
